{"Items":[{"key":"speed","attributes":[{"Name":"speed","description":"This is the MoveSpeed attribute","value":5.0,"accessModifier":"Public"}]},{"key":"gravity","attributes":[{"Name":"gravity","description":"This is the GravityForce attribute","value":20.0,"accessModifier":"Protected"}]},{"key":"multipleJumps","attributes":[{"Name":"multipleJumps","description":"This is the DoubleJump attribute","value":2.0,"accessModifier":"Private"}]},{"key":"fireballShoot","attributes":[{"Name":"fireballShoot","description":"This is the FireballShoot attribute","value":0.25,"accessModifier":"Public"}]}]}